{
    "generatedAt":  "2026-04-10T06:39:20Z",
    "accepted":  true,
    "mode":  "field-center-rk3568-routine-guard",
    "currentBoundary":  "field-center-rk3568-routine-guard-ready",
    "scope":  {
                  "target":  "center-runtime-and-rk3568-routine-operations",
                  "strictZeroNoiseRequired":  false,
                  "failureKeys":  [

                                  ]
              },
    "baselines":  {
                      "centerRuntimeFreeze":  {
                                                  "file":  "docs/unified/reports/field-center-runtime-freeze-latest.json",
                                                  "generatedAt":  "2026-04-10T06:35:24Z",
                                                  "accepted":  true,
                                                  "boundary":  "center-runtime-freeze-ready"
                                              },
                      "rk3568ProductionUplinkFreeze":  {
                                                           "file":  "docs/unified/reports/field-rk3568-production-uplink-freeze-latest.json",
                                                           "generatedAt":  "2026-04-10T06:35:30Z",
                                                           "accepted":  true,
                                                           "boundary":  "rk3568-production-uplink-freeze-ready",
                                                           "rejectedWriteFailures":  0
                                                       },
                      "operationalRecovery":  {
                                                  "file":  "docs/unified/reports/field-rk3568-center-operational-recovery-latest.json",
                                                  "generatedAt":  "2026-04-10T06:39:18Z",
                                                  "accepted":  true,
                                                  "boundary":  "rk3568-center-operational-recovery-ready",
                                                  "cleanWindowReopened":  true,
                                                  "rejectedWriteFailures":  0
                                              },
                      "phaseReadiness":  {
                                             "file":  "docs/unified/reports/field-center-deployment-software-adaptation-readiness-latest.json",
                                             "generatedAt":  "2026-04-10T06:39:18Z",
                                             "accepted":  true,
                                             "boundary":  "center-deployment-software-adaptation-ready"
                                         },
                      "centerProductionHandoff":  {
                                                      "file":  "docs/unified/reports/field-center-production-handoff-latest.json",
                                                      "generatedAt":  "2026-04-10T06:39:20Z",
                                                      "accepted":  true,
                                                      "boundary":  "center-production-handoff-ready"
                                                  }
                  },
    "nextUse":  [
                    "routine guard: powershell -NoProfile -ExecutionPolicy Bypass -File .\\scripts\\dev\\check-field-center-rk3568-routine-guard.ps1 -BoardPassword \u003cpassword\u003e -AllowUnsafeSecrets",
                    "strict routine guard: powershell -NoProfile -ExecutionPolicy Bypass -File .\\scripts\\dev\\check-field-center-rk3568-routine-guard.ps1 -BoardPassword \u003cpassword\u003e -AllowUnsafeSecrets -RequireZeroSchemaRejectedDelta",
                    "board-only recovery: powershell -NoProfile -ExecutionPolicy Bypass -File .\\scripts\\dev\\check-field-rk3568-center-operational-recovery.ps1 -BoardPassword \u003cpassword\u003e -AllowUnsafeSecrets",
                    "center-only handoff refresh: powershell -NoProfile -ExecutionPolicy Bypass -File .\\scripts\\dev\\prepare-field-center-production-handoff.ps1 -AllowUnsafeSecrets"
                ],
    "checks":  [
                   {
                       "key":  "centerRuntimeFreezeAccepted",
                       "ok":  true,
                       "actual":  true,
                       "expected":  true
                   },
                   {
                       "key":  "centerRuntimeFreezeBoundary",
                       "ok":  true,
                       "actual":  "center-runtime-freeze-ready",
                       "expected":  "center-runtime-freeze-ready"
                   },
                   {
                       "key":  "rk3568ProductionUplinkFreezeAccepted",
                       "ok":  true,
                       "actual":  true,
                       "expected":  true
                   },
                   {
                       "key":  "rk3568ProductionUplinkFreezeBoundary",
                       "ok":  true,
                       "actual":  "rk3568-production-uplink-freeze-ready",
                       "expected":  "rk3568-production-uplink-freeze-ready"
                   },
                   {
                       "key":  "rk3568ProductionRejectedWriteFailuresZero",
                       "ok":  true,
                       "actual":  0,
                       "expected":  0
                   },
                   {
                       "key":  "operationalRecoveryAccepted",
                       "ok":  true,
                       "actual":  true,
                       "expected":  true
                   },
                   {
                       "key":  "operationalRecoveryBoundary",
                       "ok":  true,
                       "actual":  "rk3568-center-operational-recovery-ready",
                       "expected":  "rk3568-center-operational-recovery-ready"
                   },
                   {
                       "key":  "operationalRecoveryRejectedWriteFailuresZero",
                       "ok":  true,
                       "actual":  0,
                       "expected":  0
                   },
                   {
                       "key":  "phaseReadinessAccepted",
                       "ok":  true,
                       "actual":  true,
                       "expected":  true
                   },
                   {
                       "key":  "phaseReadinessBoundary",
                       "ok":  true,
                       "actual":  "center-deployment-software-adaptation-ready",
                       "expected":  "center-deployment-software-adaptation-ready"
                   },
                   {
                       "key":  "centerProductionHandoffAccepted",
                       "ok":  true,
                       "actual":  true,
                       "expected":  true
                   },
                   {
                       "key":  "centerProductionHandoffBoundary",
                       "ok":  true,
                       "actual":  "center-production-handoff-ready",
                       "expected":  "center-production-handoff-ready"
                   }
               ]
}
